AUTHORS
LICENSE
MANIFEST.in
README.rst
setup.cfg
setup.py
django_iadmin.egg-info/PKG-INFO
django_iadmin.egg-info/SOURCES.txt
django_iadmin.egg-info/dependency_links.txt
django_iadmin.egg-info/not-zip-safe
django_iadmin.egg-info/requires.txt
django_iadmin.egg-info/top_level.txt
iadmin/__init__.py
iadmin/actions.py
iadmin/conf.py
iadmin/filterspecs.py
iadmin/forms.py
iadmin/media_urls.py
iadmin/models.py
iadmin/options.py
iadmin/proxy.py
iadmin/sites.py
iadmin/unicodecsv.py
iadmin/utils.py
iadmin/views.py
iadmin/widgets.py
iadmin/ajax/__init__.py
iadmin/plugins/__init__.py
iadmin/plugins/base.py
iadmin/plugins/csv/__init__.py
iadmin/plugins/csv/utils.py
iadmin/plugins/fm/__init__.py
iadmin/plugins/fm/actions.py
iadmin/plugins/fm/filemanager.py
iadmin/plugins/fm/forms.py
iadmin/plugins/fm/fs.py
iadmin/plugins/fm/utils.py
iadmin/shortcuts/__init__.py
iadmin/shortcuts/auth.py
iadmin/shortcuts/contenttypes.py
iadmin/shortcuts/djangoreversion.py
iadmin/shortcuts/flatpages.py
iadmin/shortcuts/site.py
iadmin/templates/admin/actions.html
iadmin/templates/admin/filter.html
iadmin/templates/admin/includes/csv_fieldset.html
iadmin/templates/iadmin/app_index.html
iadmin/templates/iadmin/base_site.html
iadmin/templates/iadmin/change_form_tab.html
iadmin/templates/iadmin/change_list.html
iadmin/templates/iadmin/change_list_results.html
iadmin/templates/iadmin/env_info.html
iadmin/templates/iadmin/export_csv.html
iadmin/templates/iadmin/import_csv_1.html
iadmin/templates/iadmin/import_csv_2.html
iadmin/templates/iadmin/import_csv_3.html
iadmin/templates/iadmin/index.html
iadmin/templates/iadmin/mass_update.html
iadmin/templates/iadmin/charts/index.html
iadmin/templates/iadmin/charts/model.html
iadmin/templates/iadmin/charts/test.html
iadmin/templates/iadmin/edit_inline/tabular_tab.html
iadmin/templates/iadmin/fm/index.html
iadmin/templates/iadmin/fm/upload.html
iadmin/templates/iadmin/fm/view.html
iadmin/templates/iadmin/nojs/chrome.html
iadmin/templates/iadmin/nojs/firefox.html
iadmin/templates/iadmin/nojs/ie.html
iadmin/templates/iadmin/nojs/index.html
iadmin/templates/iadmin/nojs/invalid.html
iadmin/templates/iadmin/nojs/opera.html
iadmin/templatetags/__init__.py
iadmin/templatetags/charts.py
