Metadata-Version: 1.0
Name: django-iadmin
Version: 0.1.8-alpha
Summary: UNKNOWN
Home-page: https://github.com/saxix/django-iadmin
Author: sax
Author-email: sax@os4d.org
License: BSD
Platform: any
Classifier: Development Status :: 4 - Beta
Classifier: Environment :: Web Environment
Classifier: Framework :: Django
Classifier: Operating System :: OS Independent
Classifier: Programming Language :: Python
Classifier: Intended Audience :: Developers
